README.md
setup.py
intimations/__init__.py
intimations/__main__.py
intimations/__version__.py
intimations/intimations.py
intimations.egg-info/PKG-INFO
intimations.egg-info/SOURCES.txt
intimations.egg-info/dependency_links.txt
intimations.egg-info/requires.txt
intimations.egg-info/top_level.txt
intimations/Icons/danger.ico
intimations/Icons/info.ico
intimations/Icons/sign.ico
intimations/Icons/success.ico
intimations/Icons/warning.ico
intimations/Sounds/danger.wav
intimations/Sounds/info.wav
intimations/Sounds/success.wav
intimations/Sounds/warning.wav