Metadata-Version: 2.1
Name: intimations
Version: 1.0
Summary:      Description: push notifications with different icons, beep sound with different types of sound, telegram message intimation (requires your botAPI and ChatID), command line
Home-page: https://github.com/AbhijithAJ/intimations
Author: ABHIJITH BOPPE
Author-email: abhijithas.eh@gmail.com
License: MIT
Download-URL: https://github.com/AbhijithAJ/intimations/archive/refs/tags/v1.0.tar.gz
Keywords: intimation,intimations,desktop notifications,windows notifications,cloud notification,command line notifications,process notifications,process intimationintimate after done,cross platform notifications,buzzer sound notifications,message from cloud,cloud to mobile,mobile notification after a process is done,system to mobile,laptop to mobile,cloud process intimation,sound intimations,buzzer intimations,intimate about process,inform after done,inform after complete,text when finish,messag
Platform: UNKNOWN
Classifier: Development Status :: 5 - Production/Stable
Classifier: License :: OSI Approved :: MIT License
Classifier: Programming Language :: Python
Classifier: Topic :: Software Development :: Build Tools
Classifier: Topic :: Communications
Classifier: Intended Audience :: Developers
Classifier: Intended Audience :: Information Technology
Classifier: Intended Audience :: System Administrators
Classifier: Operating System :: OS Independent
Requires-Python: >=3.2
